README.md
setup.py
colibris/__init__.py
colibris/app.py
colibris/monkey.py
colibris/pagination.py
colibris/shortcuts.py
colibris/startproject.py
colibris/utils.py
colibris.egg-info/PKG-INFO
colibris.egg-info/SOURCES.txt
colibris.egg-info/dependency_links.txt
colibris.egg-info/entry_points.txt
colibris.egg-info/requires.txt
colibris.egg-info/top_level.txt
colibris/api/__init__.py
colibris/api/envelope.py
colibris/api/exceptions.py
colibris/authentication/__init__.py
colibris/authentication/apikey.py
colibris/authentication/base.py
colibris/authentication/cookie.py
colibris/authentication/exceptions.py
colibris/authentication/jwt.py
colibris/authentication/model.py
colibris/authentication/null.py
colibris/authorization/__init__.py
colibris/authorization/base.py
colibris/authorization/exceptions.py
colibris/authorization/model.py
colibris/authorization/null.py
colibris/authorization/permissions.py
colibris/authorization/rights.py
colibris/authorization/role.py
colibris/cache/__init__.py
colibris/cache/base.py
colibris/cache/locmem.py
colibris/cache/redis.py
colibris/commands/__init__.py
colibris/commands/base.py
colibris/commands/makemigrations.py
colibris/commands/migrate.py
colibris/commands/runserver.py
colibris/commands/runworker.py
colibris/commands/shell.py
colibris/commands/test.py
colibris/conf/__init__.py
colibris/conf/backends.py
colibris/conf/schemas.py
colibris/conf/settings.py
colibris/docs/__init__.py
colibris/docs/openapi/__init__.py
colibris/docs/openapi/setup.py
colibris/docs/openapi/views.py
colibris/docs/openapi/swagger/favicon-16x16.png
colibris/docs/openapi/swagger/favicon-32x32.png
colibris/docs/openapi/swagger/index.html
colibris/docs/openapi/swagger/oauth2-redirect.html
colibris/docs/openapi/swagger/swagger-ui-bundle.js
colibris/docs/openapi/swagger/swagger-ui-bundle.js.map
colibris/docs/openapi/swagger/swagger-ui-standalone-preset.js
colibris/docs/openapi/swagger/swagger-ui-standalone-preset.js.map
colibris/docs/openapi/swagger/swagger-ui.css
colibris/docs/openapi/swagger/swagger-ui.css.map
colibris/docs/openapi/swagger/swagger-ui.js
colibris/docs/openapi/swagger/swagger-ui.js.map
colibris/email/__init__.py
colibris/email/base.py
