Metadata-Version: 2.1
Name: colibris
Version: 0.9.1
Summary: A lightweight framework for RESTful microservices
Home-page: https://github.com/colibris-framework/colibris
Author: The Colibris Team
License: BSD
Platform: UNKNOWN
